odoo9_addon_product_custom_info-9.0.1.0.0-py2.7-nspkg.pth
odoo9_addon_product_custom_info-9.0.1.0.0.dist-info/DESCRIPTION.rst
odoo9_addon_product_custom_info-9.0.1.0.0.dist-info/METADATA
odoo9_addon_product_custom_info-9.0.1.0.0.dist-info/RECORD
odoo9_addon_product_custom_info-9.0.1.0.0.dist-info/WHEEL
odoo9_addon_product_custom_info-9.0.1.0.0.dist-info/metadata.json
odoo9_addon_product_custom_info-9.0.1.0.0.dist-info/namespace_packages.txt
odoo9_addon_product_custom_info-9.0.1.0.0.dist-info/top_level.txt
odoo_addons/product_custom_info/README.rst
odoo_addons/product_custom_info/__init__.py
odoo_addons/product_custom_info/__openerp__.py
odoo_addons/product_custom_info/i18n/es.po
odoo_addons/product_custom_info/models/__init__.py
odoo_addons/product_custom_info/models/product_product.py
odoo_addons/product_custom_info/models/product_template.py
odoo_addons/product_custom_info/views/product_product_view.xml
odoo_addons/product_custom_info/views/product_template_view.xml
